wood/__init__.py
wood/comparison.py
wood/entities.py
wood/invalidate.py
wood/sync.py
wood/util.py
wood/integrations/__init__.py
wood/integrations/cloudflare.py
wood/integrations/cloudfront.py
wood/integrations/s3.py
wood/tests/__init__.py
wood/tests/test_comparison.py
wood/tests/test_util.py
wood-1.0.3.dist-info/DESCRIPTION.rst
wood-1.0.3.dist-info/METADATA
wood-1.0.3.dist-info/RECORD
wood-1.0.3.dist-info/WHEEL
wood-1.0.3.dist-info/metadata.json
wood-1.0.3.dist-info/top_level.txt
wood-1.0.3.dist-info/zip-safe
