Metadata-Version: 2.0
Name: wood
Version: 1.0.3
Summary: Compare directories, efficiently sync changes to AWS, and invalidate CDNs.
Home-page: https://github.com/gebn/wood
Author: George Brighton
Author-email: oss@gebn.co.uk
License: MIT
Platform: UNKNOWN
Classifier: Development Status :: 5 - Production/Stable
Classifier: Environment :: Console
Classifier: Intended Audience :: Developers
Classifier: License :: OSI Approved :: MIT License
Classifier: Operating System :: OS Independent
Classifier: Programming Language :: Python
Classifier: Programming Language :: Python :: 3 :: Only
Classifier: Programming Language :: Python :: 3.6
Classifier: Programming Language :: Python :: 3.7
Classifier: Topic :: Software Development :: Libraries :: Python Modules
Requires-Dist: backoff
Requires-Dist: boto3
Requires-Dist: botocore
Requires-Dist: more-itertools
Requires-Dist: requests
